odarchive/__init__.py
odarchive/_version.py
odarchive/abstract_file_db.py
odarchive/archive.py
odarchive/cli.py
odarchive/consts.py
odarchive/disc_info.py
odarchive/file_db.py
odarchive/file_entry.py
odarchive/hash_db.py
odarchive/hash_file_entry.py
odarchive/tools.py
odarchive-0.1.0.dist-info/LICENSE
odarchive-0.1.0.dist-info/METADATA
odarchive-0.1.0.dist-info/WHEEL
odarchive-0.1.0.dist-info/top_level.txt
odarchive-0.1.0.dist-info/RECORD
