Metadata-Version: 2.1
Name: odarchive
Version: 0.1.0
Summary: Convert file systems to archiveable ISO files
Home-page: https://github.com/drummonds/odarchive
Author: Humphrey Drummond
Author-email: hum3@drummond.info
License: MIT license
Keywords: cdrom,dvd,bdrom,archive,odarchive
Platform: UNKNOWN
Classifier: Development Status :: 3 - Alpha
Classifier: Intended Audience :: Developers
Classifier: License :: OSI Approved :: MIT License
Classifier: Natural Language :: English
Classifier: Programming Language :: Python :: 3
Classifier: Programming Language :: Python :: 3.6
Requires-Dist: python-dateutil
